mokarakaya_pytest_notes/__init__.py
mokarakaya_pytest_notes/source/__init__.py
mokarakaya_pytest_notes/source/capitalize.py
mokarakaya_pytest_notes/source/manager.py
mokarakaya_pytest_notes/test/__init__.py
mokarakaya_pytest_notes/test/test_capitalize.py
mokarakaya_pytest_notes/test/test_manager.py
mokarakaya_machine_learning_and_python_notes-0.0.3.dist-info/METADATA
mokarakaya_machine_learning_and_python_notes-0.0.3.dist-info/WHEEL
mokarakaya_machine_learning_and_python_notes-0.0.3.dist-info/top_level.txt
mokarakaya_machine_learning_and_python_notes-0.0.3.dist-info/RECORD
