Metadata-Version: 2.1
Name: mokarakaya-machine-learning-and-python-notes
Version: 0.0.3
Summary: Python notes with examples
Home-page: https://github.com/mokarakaya/machine-learning-and-python-notes
Author: mokarakaya
Author-email: mokarakaya@gmail.com
License: UNKNOWN
Platform: UNKNOWN
Classifier: Programming Language :: Python :: 3
Classifier: Operating System :: OS Independent
Requires-Python: >=3.6
Requires-Dist: mock (==4.0.2)
Requires-Dist: pytest-mock (==3.1.0)
Requires-Dist: pytest (==5.4.2)
